{
  "Sunrisers Hyderabad": {
    "winner": 42,
    "toss_winner": 35
  },
  "Rising Pune Supergiant": {
    "winner": 10,
    "toss_winner": 6
  },
  "Kolkata Knight Riders": {
    "winner": 77,
    "toss_winner": 78
  },
  "Kings XI Punjab": {
    "winner": 70,
    "toss_winner": 68
  },
  "Royal Challengers Bangalore": {
    "winner": 73,
    "toss_winner": 69
  },
  "Mumbai Indians": {
    "winner": 92,
    "toss_winner": 85
  },
  "Delhi Daredevils": {
    "winner": 62,
    "toss_winner": 72
  },
  "Gujarat Lions": {
    "winner": 13,
    "toss_winner": 15
  },
  "Chennai Super Kings": {
    "winner": 79,
    "toss_winner": 66
  },
  "Rajasthan Royals": {
    "winner": 63,
    "toss_winner": 62
  },
  "Deccan Chargers": {
    "winner": 29,
    "toss_winner": 41
  },
  "Pune Warriors": {
    "winner": 12,
    "toss_winner": 20
  },
  "Kochi Tuskers Kerala": {
    "winner": 6,
    "toss_winner": 6
  },
  "": {
    "winner": 3
  },
  "Rising Pune Supergiants": {
    "winner": 5,
    "toss_winner": 7
  }
}